mwplotlib/__init__.py
mwplotlib/arms_data.py
mwplotlib/spiral_arms.py
mwplotlib/utilities.py
mwplotlib/data/apjacc45ct1_mrt.txt
mwplotlib/data/apjacc45ct2_ascii.txt
mwplotlib-1.1.3.dist-info/LICENSE
mwplotlib-1.1.3.dist-info/METADATA
mwplotlib-1.1.3.dist-info/WHEEL
mwplotlib-1.1.3.dist-info/top_level.txt
mwplotlib-1.1.3.dist-info/RECORD
