Metadata-Version: 2.1
Name: mwplotlib
Version: 1.1.3
Summary: The Milky Way Plotting Library
Home-page: https://github.com/xiawenke/mwplotlib
Author: Wenky
Author-email: wxia1@fandm.edu
License-File: LICENSE
Requires-Dist: astropy
Requires-Dist: numpy
Requires-Dist: pandas
Requires-Dist: matplotlib
